CHANGES
MANIFEST.in
README
setup.py
Schema_Sync.egg-info/PKG-INFO
Schema_Sync.egg-info/SOURCES.txt
Schema_Sync.egg-info/dependency_links.txt
Schema_Sync.egg-info/entry_points.txt
Schema_Sync.egg-info/requires.txt
Schema_Sync.egg-info/top_level.txt
schema_sync.egg-info/PKG-INFO
schema_sync.egg-info/SOURCES.txt
schema_sync.egg-info/dependency_links.txt
schema_sync.egg-info/entry_points.txt
schema_sync.egg-info/requires.txt
schema_sync.egg-info/top_level.txt
schemasync/__init__.py
schemasync/schemasync.py
schemasync/syncdb.py
schemasync/utils.py