Metadata-Version: 1.1
Name: Schema-Sync
Version: 0.9.7
Summary: A MySQL Schema Synchronization Utility
Home-page: https://github.com/hhyo/SchemaSync
Author: Mitch Matuson, Mustafa Ozgur
Author-email: UNKNOWN
License: UNKNOWN
Keywords: MySQL,database,schema,migration,SQL
Platform: UNKNOWN
Classifier: Environment :: Console
Classifier: Intended Audience :: Information Technology
Classifier: Intended Audience :: System Administrators
Classifier: Intended Audience :: Developers
Classifier: License :: OSI Approved :: Apache Software License
Classifier: Programming Language :: Python
Classifier: Topic :: Database
Classifier: Topic :: Database :: Front-Ends
Classifier: Topic :: Software Development :: Build Tools
Classifier: Topic :: Software Development :: Code Generators
Classifier: Topic :: Utilities
